phenofetch/__init__.py
phenofetch/cam_meta.py
phenofetch/daily_links.py
phenofetch/phenofetch.py
phenofetch/site_info.py
phenofetch/site_stats.py
phenofetch/size_estimate.py
phenofetch-0.2.1.dist-info/licenses/LICENSE
phenofetch-0.2.1.dist-info/METADATA
phenofetch-0.2.1.dist-info/WHEEL
phenofetch-0.2.1.dist-info/entry_points.txt
phenofetch-0.2.1.dist-info/top_level.txt
phenofetch-0.2.1.dist-info/RECORD
