Metadata-Version: 2.4
Name: phenofetch
Version: 0.2.1
Summary: Command-line tool for downloading PhenoCam data
Home-page: https://github.com/samapriya/phenofetch
Author: Samapriya Roy
Author-email: samapriya.roy@gmail.com
Classifier: Development Status :: 4 - Beta
Classifier: Intended Audience :: Developers
Classifier: Intended Audience :: Science/Research
Classifier: Topic :: Scientific/Engineering :: GIS
Classifier: Programming Language :: Python :: 3
Classifier: License :: OSI Approved :: Apache Software License
Classifier: Operating System :: OS Independent
Requires-Python: >=3.9
License-File: LICENSE
Requires-Dist: setuptools
Requires-Dist: wheel
Requires-Dist: requests
Requires-Dist: pandas
Requires-Dist: beautifulsoup4
Requires-Dist: aiofiles
Requires-Dist: aiohttp
Requires-Dist: psutil
Requires-Dist: rich
Requires-Dist: tqdm
Requires-Dist: colorama
Dynamic: author
Dynamic: author-email
Dynamic: classifier
Dynamic: description
Dynamic: description-content-type
Dynamic: home-page
Dynamic: license-file
Dynamic: requires-dist
Dynamic: requires-python
Dynamic: summary
